statlearn/__init__.py
statlearn/statlearn.py
statlearn-0.0.1.dist-info/LICENSE
statlearn-0.0.1.dist-info/METADATA
statlearn-0.0.1.dist-info/WHEEL
statlearn-0.0.1.dist-info/top_level.txt
statlearn-0.0.1.dist-info/RECORD
