Metadata-Version: 2.1
Name: statlearn
Version: 0.0.1
Summary: statistical learning
Home-page: https://github.com/pypa/statlearn
Author: Maxime Logé
Author-email: max.loge@gmail.com
License: UNKNOWN
Project-URL: Bug Tracker, https://github.com/pypa/sampleproject/issues
Platform: UNKNOWN
Classifier: Programming Language :: Python :: 3
Classifier: License :: OSI Approved :: Apache Software License
Classifier: Operating System :: OS Independent
Requires-Python: >=3.6
License-File: LICENSE
